[{
		"name": "Explore",
		"visibility_rules": ["exploreCheck"],
		"children": [{
				"name": "Distant Roost Chest",
				"access_rules": [
					"Distant Roost"
				],
				"sections": [{
				"name": "1",
					"clear_as_group": false,
					"item_count": 20
				}
				],
				"map_locations": [{
					"map": "map1",
					"x": 170,
					"y": 52
				}]
			},
			{
				"name": "Distant Roost Shrine",
				"access_rules": [
					"Distant Roost"
				],
				"sections": [{
				"name": "1",
					"clear_as_group": false,
					"item_count": 20
				}
				],
				"map_locations": [{
					"map": "map1",
					"x": 170,
					"y": 80
				}]
			},
			{
				"name": "Distant Roost Newt Altar",
				"access_rules": [
					"Distant Roost"
				],
				"sections": [{
				"name": "1",
					"clear_as_group": false,
					"item_count": 2
				}
				],
				"map_locations": [{
					"map": "map1",
					"x": 170,
					"y": 108
				}]
			},
			{
				"name": "Distant Roost Radio Scanner",
				"access_rules": [
					"Distant Roost"
				],
				"sections": [{
				"name": "1",
					"clear_as_group": false,
					"item_count": 1
				}
				],
				"map_locations": [{
					"map": "map1",
					"x": 170,
					"y": 136
				}]
			},
			{
				"name": "Distant Roost Scavenger",
				"access_rules": [
					"Distant Roost,[$Zone1Access],[$Zone2Access],[$Zone3Access],[$Zone4Access],[$Zone5Access]"
				],
				"sections": [{
				"name": "1",
					"clear_as_group": false,
					"item_count": 1
				}
				],
				"map_locations": [{
					"map": "map1",
					"x": 170,
					"y": 164
				}]
			},
			{
				"name": "Distant Roost (2) Chest",
				"access_rules": [
					"Distant Roost (2)"
				],
				"sections": [{
				"name": "1",
					"clear_as_group": true,
					"item_count": 20
				}
				],
				"map_locations": [{
					"map": "map1",
					"x": 352,
					"y": 52
				}]
			},
			{
				"name": "Distant Roost (2) Shrine",
				"access_rules": [
					"Distant Roost (2)"
				],
				"sections": [{
				"name": "1",
					"clear_as_group": false,
					"item_count": 20
				}
				],
				"map_locations": [{
					"map": "map1",
					"x": 352,
					"y": 80
				}]
			},{
				"name": "Distant Roost (2) Newt Altar",
				"access_rules": [
					"Distant Roost (2)"
				],
				"sections": [{
				"name": "1",
					"clear_as_group": false,
					"item_count": 2
				}
				],
				"map_locations": [{
					"map": "map1",
					"x": 352,
					"y": 108
				}]
			},
			{
				"name": "Distant Roost (2) Radio Scanner",
				"access_rules": [
					"Distant Roost (2)"
				],
				"sections": [{
				"name": "1",
					"clear_as_group": false,
					"item_count": 1
				}
				],
				"map_locations": [{
					"map": "map1",
					"x": 352,
					"y": 136
				}]
			},
			{
				"name": "Distant Roost (2) Scavenger",
				"access_rules": [
					"Distant Roost (2),[$Zone1Access],[$Zone2Access],[$Zone3Access],[$Zone4Access],[$Zone5Access]"
				],
				"sections": [{
				"name": "1",
					"clear_as_group": false,
					"item_count": 1
				}
				],
				"map_locations": [{
					"map": "map1",
					"x": 352,
					"y": 164
				}]
			},
			{
				"name": "Abandoned Aqueduct Chest",
				"access_rules": [
					"{Abandoned Aqueduct}",
					"$Zone1Access,Abandoned Aqueduct"
				],
				"sections": [{
				"name": "1",
					"clear_as_group": false,
					"item_count": 20
				}
				],
				"map_locations": [{
					"map": "map1",
					"x": 610,
					"y": 52
				}]
			},
			{
				"name": "Abandoned Aqueduct Shrine",
				"access_rules": [
					"{Abandoned Aqueduct}",
					"$Zone1Access,Abandoned Aqueduct"
				],
				"sections": [{
				"name": "1",
					"clear_as_group": false,
					"item_count": 20
				}
				],
				"map_locations": [{
					"map": "map1",
					"x": 610,
					"y": 80
				}]
			},{
				"name": "Abandoned Aqueduct Newt Altar",
				"access_rules": [
					"{Abandoned Aqueduct}",
					"$Zone1Access,Abandoned Aqueduct"
				],
				"sections": [{
				"name": "1",
					"clear_as_group": false,
					"item_count": 2
				}
				],
				"map_locations": [{
					"map": "map1",
					"x": 610,
					"y": 108
				}]
			},
			{
				"name": "Abandoned Aqueduct Radio Scanner",
				"access_rules": [
					"{Abandoned Aqueduct}",
					"$Zone1Access, Abandoned Aqueduct"
				],
				"sections": [{
				"name": "1",
					"clear_as_group": false,
					"item_count": 1
				}
				],
				"map_locations": [{
					"map": "map1",
					"x": 610,
					"y": 136
				}]
			},
			{
				"name": "Abandoned Aqueduct Scavenger",
				"access_rules": [
					"{Abandoned Aqueduct}",
					"Abandoned Aqueduct,$Zone1Access,[$Zone2Access],[$Zone3Access],[$Zone4Access],[$Zone5Access]"
				],
				"sections": [{
				"name": "1",
					"clear_as_group": false,
					"item_count": 1
				}
				],
				"map_locations": [{
					"map": "map1",
					"x": 610,
					"y": 164
				}]
			},
			{
				"name": "Abyssal Depths Chest",
				"access_rules": [
					"{Abyssal Depths}",
					"$Zone1Access,$Zone2Access,$Zone3Access,Abyssal Depths"
				],
				"sections": [{
				"name": "1",
					"clear_as_group": false,
					"item_count": 20
				}
				],
				"map_locations": [{
					"map": "map1",
					"x": 1065,
					"y": 52
				}]
			},
			{
				"name": "Abyssal Depths Shrine",
				"access_rules": [
					"{Abyssal Depths}",
					"$Zone1Access,$Zone2Access,$Zone3Access,Abyssal Depths"
				],
				"sections": [{
				"name": "1",
					"clear_as_group": false,
					"item_count": 20
				}
				],
				"map_locations": [{
					"map": "map1",
					"x": 1065,
					"y": 80
				}]
			},{
				"name": "Abyssal Depths Newt Altar",
				"access_rules": [
					"{Abyssal Depths}",
					"$Zone1Access,$Zone2Access,$Zone3Access,Abyssal Depths"
				],
				"sections": [{
				"name": "1",
					"clear_as_group": false,
					"item_count": 2
				}
				],
				"map_locations": [{
					"map": "map1",
					"x": 1065,
					"y": 108
				}]
			},
			{
				"name": "Abyssal Depths Radio Scanner",
				"access_rules": [
					"{Abyssal Depths}",
					"$Zone1Access,$Zone2Access,$Zone3Access,Abyssal Depths"
				],
				"sections": [{
				"name": "1",
					"clear_as_group": false,
					"item_count": 1
				}
				],
				"map_locations": [{
					"map": "map1",
					"x": 1065,
					"y": 136
				}]
			},
			{
				"name": "Abyssal Depths Scavenger",
				"access_rules": [
					"{Abyssal Depths}",
					"$Zone1Access,$Zone2Access,$Zone3Access,[$Zone4Access],[$Zone5Access],Abyssal Depths"
				],
				"sections": [{
				"name": "1",
					"clear_as_group": false,
					"item_count": 1
				}
				],
				"map_locations": [{
					"map": "map1",
					"x": 1065,
					"y": 164
				}]
			},
			{
				"name": "Aphelian Sanctuary Chest",
				"access_rules": [
					"{Aphelian Sanctuary}",
					"$Zone1Access,Aphelian Sanctuary"
				],
				"sections": [{
				"name": "1",
					"clear_as_group": false,
					"item_count": 20
				}
				],
				"map_locations": [{
					"map": "map1",
					"x": 610,
					"y": 400
				}]
			},
			{
				"name": "Aphelian Sanctuary Shrine",
				"access_rules": [
					"{Aphelian Sanctuary}",
					"$Zone1Access,Aphelian Sanctuary"
				],
				"sections": [{
				"name": "1",
					"clear_as_group": false,
					"item_count": 20
				}
				],
				"map_locations": [{
					"map": "map1",
					"x": 610,
					"y": 428
				}]
			},{
				"name": "Aphelian Sanctuary Newt Altar",
				"access_rules": [
					"{Aphelian Sanctuary}",
					"$Zone1Access,Aphelian Sanctuary"
				],
				"sections": [{
				"name": "1",
					"clear_as_group": false,
					"item_count": 2
				}
				],
				"map_locations": [{
					"map": "map1",
					"x": 610,
					"y": 456
				}]
			},
			{
				"name": "Aphelian Sanctuary Radio Scanner",
				"access_rules": [
					"{Aphelian Sanctuary}",
					"$Zone1Access,Aphelian Sanctuary"
				],
				"sections": [{
				"name": "1",
					"clear_as_group": false,
					"item_count": 1
				}
				],
				"map_locations": [{
					"map": "map1",
					"x": 610,
					"y": 484
				}]
			},
			{
				"name": "Aphelian Sanctuary Scavenger",
				"access_rules": [
					"{Aphelian Sanctuary}",
					"$Zone1Access,[$Zone2Access],[$Zone3Access],[$Zone4Access],[$Zone5Access],Aphelian Sanctuary"
				],
				"sections": [{
				"name": "1",
					"clear_as_group": false,
					"item_count": 1
				}
				],
				"map_locations": [{
					"map": "map1",
					"x": 610,
					"y": 512
				}]
			},
			{
				"name": "Rallypoint Delta Chest",
				"access_rules": [
				"$Zone1Access,$Zone2Access,Rallypoint Delta",
				"{Rallypoint Delta}"
				],
				"sections": [{
				"name": "1",
					"clear_as_group": false,
					"item_count": 20
				}
				],
				"map_locations": [{
					"map": "map1",
					"x": 825,
					"y": 52
				}]
			},
			{
				"name": "Rallypoint Delta Shrine",
				"access_rules": [
				"$Zone1Access,$Zone2Access,Rallypoint Delta",
				"{Rallypoint Delta}"
				],
				"sections": [{
				"name": "1",
					"clear_as_group": false,
					"item_count": 20
				}
				],
				"map_locations": [{
					"map": "map1",
					"x": 825,
					"y": 80
				}]
			},{
				"name": "Rallypoint Delta Newt Altar",
				"access_rules": [
				"$Zone1Access,$Zone2Access,Rallypoint Delta",
				"{Rallypoint Delta}"
				],
				"sections": [{
				"name": "1",
					"clear_as_group": false,
					"item_count": 2
				}
				],
				"map_locations": [{
					"map": "map1",
					"x": 825,
					"y": 108
				}]
			},
			{
				"name": "Rallypoint Delta Radio Scanner",
				"access_rules": [
				"$Zone1Access,$Zone2Access,Rallypoint Delta",
				"{Rallypoint Delta}"
				],
				"sections": [{
				"name": "1",
					"clear_as_group": false,
					"item_count": 1
				}
				],
				"map_locations": [{
					"map": "map1",
					"x": 825,
					"y": 136
				}]
			},
			{
				"name": "Rallypoint Delta Scavenger",
				"access_rules": [
					"{Rallypoint Delta}",
					"$Zone1Access,$Zone2Access,[$Zone3Access],[$Zone4Access],[$Zone5Access],Rallypoint Delta"
				],
				"sections": [{
				"name": "1",
					"clear_as_group": false,
					"item_count": 1
				}
				],
				"map_locations": [{
					"map": "map1",
					"x": 825,
					"y": 164
				}]
			},
			{
				"name": "Scorched Acres Chest",
				"access_rules": [
					"{Scorched Acres}",
					"$Zone1Access,$Zone2Access,Scorched Acres"
				],
				"sections": [{
				"name": "1",
					"clear_as_group": false,
					"item_count": 20
				}
				],
				"map_locations": [{
					"map": "map1",
					"x": 825,
					"y": 226
				}]
			},
			{
				"name": "Scorched Acres Shrine",
				"access_rules": [
					"{Scorched Acres}",
					"$Zone1Access,$Zone2Access,Scorched Acres"
				],
				"sections": [{
				"name": "1",
					"clear_as_group": false,
					"item_count": 20
				}
				],
				"map_locations": [{
					"map": "map1",
					"x": 825,
					"y": 254
				}]
			},{
				"name": "Scorched Acres Newt Altar",
				"access_rules": [
					"{Scorched Acres}",
					"$Zone1Access,$Zone2Access,Scorched Acres"
				],
				"sections": [{
				"name": "1",
					"clear_as_group": false,
					"item_count": 2
				}
				],
				"map_locations": [{
					"map": "map1",
					"x": 825,
					"y": 282
				}]
			},
			{
				"name": "Scorched Acres Radio Scanner",
				"access_rules": [
					"{Scorched Acres}",
					"$Zone1Access,$Zone2Access,Scorched Acres"
				],
				"sections": [{
				"name": "1",
					"clear_as_group": false,
					"item_count": 1
				}
				],
				"map_locations": [{
					"map": "map1",
					"x": 825,
					"y": 310
				}]
			},
			{
				"name": "Scorched Acres Scavenger",
				"access_rules": [
					"{Scorched Acres}",
					"$Zone1Access,$Zone2Access,[$Zone3Access],[$Zone4Access],[$Zone5Access],Scorched Acres"
				],
				"sections": [{
				"name": "1",
					"clear_as_group": false,
					"item_count": 1
				}
				],
				"map_locations": [{
					"map": "map1",
					"x": 825,
					"y": 338
				}]
			},
			{
				"name": "Siphoned Forest Chest",
				"access_rules": [
					"Siphoned Forest"
				],
				"sections": [{
				"name": "1",
					"clear_as_group": false,
					"item_count": 20
				}
				],
				"map_locations": [{
					"map": "map1",
					"x": 170,
					"y": 752
				}]
			},
			{
				"name": "Siphoned Forest Shrine",
				"access_rules": [
					"Siphoned Forest"
				],
				"sections": [{
				"name": "1",
					"clear_as_group": false,
					"item_count": 20
				}
				],
				"map_locations": [{
					"map": "map1",
					"x": 170,
					"y": 780
				}]
			},{
				"name": "Siphoned Forest Newt Altar",
				"access_rules": [
					"Siphoned Forest"
				],
				"sections": [{
				"name": "1",
					"clear_as_group": false,
					"item_count": 2
				}
				],
				"map_locations": [{
					"map": "map1",
					"x": 170,
					"y": 808
				}]
			},
			{
				"name": "Siphoned Forest Radio Scanner",
				"access_rules": [
					"Siphoned Forest"
				],
				"sections": [{
				"name": "1",
					"clear_as_group": false,
					"item_count": 1
				}
				],
				"map_locations": [{
					"map": "map1",
					"x": 170,
					"y": 836
				}]
			},
			{
				"name": "Siphoned Forest Scavenger",
				"access_rules": [
					"[$Zone1Access],[$Zone2Access],[$Zone3Access],[$Zone4Access],[$Zone5Access],Siphoned Forest"
				],
				"sections": [{
				"name": "1",
					"clear_as_group": false,
					"item_count": 1
				}
				],
				"map_locations": [{
					"map": "map1",
					"x": 170,
					"y": 864
				}]
			},
			{
				"name": "Sirens Call Chest",
				"access_rules": [
					"{Sirens Call}",
					"$Zone1Access,$Zone2Access,$Zone3Access,Sirens Call"
				],
				"sections": [{
				"name": "1",
					"clear_as_group": false,
					"item_count": 20
				}
				],
				"map_locations": [{
					"map": "map1",
					"x": 1065,
					"y": 226
				}]
			},
			{
				"name": "Sirens Call Shrine",
				"access_rules": [
					"{Sirens Call}",
					"$Zone1Access,$Zone2Access,$Zone3Access,Sirens Call"
				],
				"sections": [{
				"name": "1",
					"clear_as_group": false,
					"item_count": 20
				}
				],
				"map_locations": [{
					"map": "map1",
					"x": 1065,
					"y": 254
				}]
			},{
				"name": "Sirens Call Newt Altar",
				"access_rules": [
					"{Sirens Call}",
					"$Zone1Access,$Zone2Access,$Zone3Access,Sirens Call"
				],
				"sections": [{
				"name": "1",
					"clear_as_group": false,
					"item_count": 2
				}
				],
				"map_locations": [{
					"map": "map1",
					"x": 1065,
					"y": 282
				}]
			},
			{
				"name": "Sirens Call Radio Scanner",
				"access_rules": [
					"{Sirens Call}",
					"$Zone1Access,$Zone2Access,$Zone3Access,Sirens Call"
				],
				"sections": [{
				"name": "1",
					"clear_as_group": false,
					"item_count": 1
				}
				],
				"map_locations": [{
					"map": "map1",
					"x": 1065,
					"y": 310
				}]
			},
			{
				"name": "Sirens Call Scavenger",
				"access_rules": [
					"{Sirens Call}",
					"$Zone1Access,$Zone2Access,$Zone3Access,[$Zone4Access],[$Zone5Access],Sirens Call"
				],
				"sections": [{
				"name": "1",
					"clear_as_group": false,
					"item_count": 1
				}
				],
				"map_locations": [{
					"map": "map1",
					"x": 1065,
					"y": 338
				}]
			},
			{
				"name": "Sky Meadow Chest",
				"access_rules": [
					"{Sky Meadow}",
					"$Zone1Access,$Zone2Access,$Zone3Access,$Zone4Access,Sky Meadow"
				],
				"sections": [{
				"name": "1",
					"clear_as_group": false,
					"item_count": 20
				}
				],
				"map_locations": [{
					"map": "map1",
					"x": 1290,
					"y": 52
				}]
			},
			{
				"name": "Sky Meadow Shrine",
								"access_rules": [
					"{Sky Meadow}",
					"$Zone1Access,$Zone2Access,$Zone3Access,$Zone4Access,Sky Meadow"
				],
				"sections": [{
				"name": "1",
					"clear_as_group": false,
					"item_count": 20
				}
				],
				"map_locations": [{
					"map": "map1",
					"x": 1290,
					"y": 80
				}]
			},{
				"name": "Sky Meadow Newt Altar",
								"access_rules": [
					"{Sky Meadow}",
					"$Zone1Access,$Zone2Access,$Zone3Access,$Zone4Access,Sky Meadow"
				],
				"sections": [{
				"name": "1",
					"clear_as_group": false,
					"item_count": 2
				}
				],
				"map_locations": [{
					"map": "map1",
					"x": 1290,
					"y": 108
				}]
			},
			{
				"name": "Sky Meadow Radio Scanner",
								"access_rules": [
					"{Sky Meadow}",
					"$Zone1Access,$Zone2Access,$Zone3Access,$Zone4Access,Sky Meadow"
				],
				"sections": [{
				"name": "1",
					"clear_as_group": false,
					"item_count": 1
				}
				],
				"map_locations": [{
					"map": "map1",
					"x": 1290,
					"y": 170
				}]
			},
			{
				"name": "Sky Meadow Scavenger",
				"access_rules": [
					"{Sky Meadow}",
					"$Zone1Access,$Zone2Access,$Zone3Access,$Zone4Access,Sky Meadow"
				],
				"sections": [{
				"name": "1",
					"clear_as_group": false,
					"item_count": 1
				}
				],
				"map_locations": [{
					"map": "map1",
					"x": 1290,
					"y": 164
				}]
			},
			{
				"name": "Sulfur Pools Chest",
				"access_rules": [
					"{Sulfur Pools}",
					"$Zone1Access,$Zone2Access,Sulfur Pools"
				],
				"sections": [{
				"name": "1",
					"clear_as_group": false,
					"item_count": 20
				}
				],
				"map_locations": [{
					"map": "map1",
					"x": 825,
					"y": 400
				}]
			},
			{
				"name": "Sulfur Pools Shrine",
				"access_rules": [
					"{Sulfur Pools}",
					"$Zone1Access,$Zone2Access,Sulfur Pools"
				],
				"sections": [{
				"name": "1",
					"clear_as_group": false,
					"item_count": 20
				}
				],
				"map_locations": [{
					"map": "map1",
					"x": 825,
					"y": 428
				}]
			},{
				"name": "Sulfur Pools Newt Altar",
				"access_rules": [
					"{Sulfur Pools}",
					"$Zone1Access,$Zone2Access,Sulfur Pools"
				],
				"sections": [{
				"name": "1",
					"clear_as_group": false,
					"item_count": 2
				}
				],
				"map_locations": [{
					"map": "map1",
					"x": 825,
					"y": 456
				}]
			},
			{
				"name": "Sulfur Pools Radio Scanner",
				"access_rules": [
					"{Sulfur Pools}",
					"$Zone1Access,$Zone2Access,Sulfur Pools"
				],
				"sections": [{
				"name": "1",
					"clear_as_group": false,
					"item_count": 1
				}
				],
				"map_locations": [{
					"map": "map1",
					"x": 825,
					"y": 484
				}]
			},
			{
				"name": "Sulfur Pools Scavenger",
				"access_rules": [
					"{Sulfur Pools}",
					"$Zone1Access,$Zone2Access,[$Zone3Access],[$Zone4Access],[$Zone5Access],Sulfur Pools"
				],
				"sections": [{
				"name": "1",
					"clear_as_group": false,
					"item_count": 1
				}
				],
				"map_locations": [{
					"map": "map1",
					"x": 825,
					"y": 512
				}]
			},
			{
				"name": "Sundered Grove Chest",
				"access_rules": [
					"{Sundered Grove}",
					"$Zone1Access,$Zone2Access,$Zone3Access,Sundered Grove"
				],
				"sections": [{
				"name": "1",
					"clear_as_group": false,
					"item_count": 20
				}
				],
				"map_locations": [{
					"map": "map1",
					"x": 1065,
					"y": 400
				}]
			},
			{
				"name": "Sundered Grove Shrine",
				"access_rules": [
					"{Sundered Grove}",
					"$Zone1Access,$Zone2Access,$Zone3Access,Sundered Grove"
				],
				"sections": [{
				"name": "1",
					"clear_as_group": false,
					"item_count": 20
				}
				],
				"map_locations": [{
					"map": "map1",
					"x": 1065,
					"y": 428
				}]
			},{
				"name": "Sundered Grove Newt Altar",
				"access_rules": [
					"{Sundered Grove}",
					"$Zone1Access,$Zone2Access,$Zone3Access,Sundered Grove"
				],
				"sections": [{
				"name": "1",
					"clear_as_group": false,
					"item_count": 2
				}
				],
				"map_locations": [{
					"map": "map1",
					"x": 1065,
					"y": 456
				}]
			},
			{
				"name": "Sundered Grove Radio Scanner",
				"access_rules": [
					"{Sundered Grove}",
					"$Zone1Access,$Zone2Access,$Zone3Access,Sundered Grove"
				],
				"sections": [{
				"name": "1",
					"clear_as_group": false,
					"item_count": 1
				}
				],
				"map_locations": [{
					"map": "map1",
					"x": 1065,
					"y": 484
				}]
			},
			{
				"name": "Sundered Grove Scavenger",
				"access_rules": [
					"{Sundered Grove}",
					"$Zone1Access,$Zone2Access,$Zone3Access,[$Zone4Access],[$Zone5Access],Sundered Grove"
				],
				"sections": [{
				"name": "1",
					"clear_as_group": false,
					"item_count": 1
				}
				],
				"map_locations": [{
					"map": "map1",
					"x": 1065,
					"y": 512
				}]
			},
			{
				"name": "Titanic Plains (2) Chest",
				"access_rules": [
					"Titanic Plains (2)"
				],
				"sections": [{
				"name": "1",
					"clear_as_group": false,
					"item_count": 20
				}
				],
				"map_locations": [{
					"map": "map1",
					"x": 352,
					"y": 226
				}]
			},
			{
				"name": "Titanic Plains (2) Shrine",
				"access_rules": [
					"Titanic Plains (2)"
				],
				"sections": [{
				"name": "1",
					"clear_as_group": false,
					"item_count": 20
				}
				],
				"map_locations": [{
					"map": "map1",
					"x": 352,
					"y": 254
				}]
			},{
				"name": "Titanic Plains (2) Newt Altar",
				"access_rules": [
					"Titanic Plains (2)"
				],
				"sections": [{
				"name": "1",
					"clear_as_group": false,
					"item_count": 2
				}
				],
				"map_locations": [{
					"map": "map1",
					"x": 352,
					"y": 282
				}]
			},
			{
				"name": "Titanic Plains (2) Radio Scanner",
				"access_rules": [
					"Titanic Plains (2)"
				],
				"sections": [{
				"name": "1",
					"clear_as_group": false,
					"item_count": 1
				}
				],
				"map_locations": [{
					"map": "map1",
					"x": 352,
					"y": 310
				}]
			},
			{
				"name": "Titanic Plains (2) Scavenger",
				"access_rules": [
					"[$Zone1Access],[$Zone2Access],[$Zone3Access],[$Zone4Access],[$Zone5Access],Titanic Plains (2)"
				],
				"sections": [{
				"name": "1",
					"clear_as_group": false,
					"item_count": 1
				}
				],
				"map_locations": [{
					"map": "map1",
					"x": 352,
					"y": 338
				}]
			},
			{
				"name": "Titanic Plains Chest",
				"access_rules": [
					"Titanic Plains"
				],
				"sections": [{
				"name": "1",
					"clear_as_group": false,
					"item_count": 20
				}
				],
				"map_locations": [{
					"map": "map1",
					"x": 170,
					"y": 226
				}]
			},
			{
				"name": "Titanic Plains Shrine",
				"access_rules": [
					"Titanic Plains"
				],
				"sections": [{
				"name": "1",
					"clear_as_group": false,
					"item_count": 20
				}
				],
				"map_locations": [{
					"map": "map1",
					"x": 170,
					"y": 254
				}]
			},{
				"name": "Titanic Plains Newt Altar",
				"access_rules": [
					"Titanic Plains"
				],
				"sections": [{
				"name": "1",
					"clear_as_group": false,
					"item_count": 2
				}
				],
				"map_locations": [{
					"map": "map1",
					"x": 170,
					"y": 282
				}]
			},
			{
				"name": "Titanic Plains Radio Scanner",
				"access_rules": [
					"Titanic Plains"
				],
				"sections": [{
				"name": "1",
					"clear_as_group": false,
					"item_count": 1
				}
				],
				"map_locations": [{
					"map": "map1",
					"x": 170,
					"y": 310
				}]
			},
			{
				"name": "Titanic Plains Scavenger",
				"access_rules": [
					"[$Zone1Access],[$Zone2Access],[$Zone3Access],[$Zone4Access],[$Zone5Access],Titanic Plains"
				],
				"sections": [{
				"name": "1",
					"clear_as_group": false,
					"item_count": 1
				}
				],
				"map_locations": [{
					"map": "map1",
					"x": 170,
					"y": 338
				}]
			},
			{
				"name": "Wetland Aspect Chest",
				"access_rules": [
				"$Zone1Access,Wetland Aspect",
				"{Wetland Aspect}"
				],
				"sections": [{
				"name": "1",
					"clear_as_group": false,
					"item_count": 20
				}
				],
				"map_locations": [{
					"map": "map1",
					"x": 610,
					"y": 226
				}]
			},
			{
				"name": "Wetland Aspect Shrine",
				"access_rules": [
				"$Zone1Access,Wetland Aspect",
				"{Wetland Aspect}"
				],
				"sections": [{
				"name": "1",
					"clear_as_group": false,
					"item_count": 20
				}
				],
				"map_locations": [{
					"map": "map1",
					"x": 610,
					"y": 254
				}]
			},{
				"name": "Wetland Aspect Newt Altar",
				"access_rules": [
				"$Zone1Access,Wetland Aspect",
				"{Wetland Aspect}"
				],
				"sections": [{
				"name": "1",
					"clear_as_group": false,
					"item_count": 2
				}
				],
				"map_locations": [{
					"map": "map1",
					"x": 610,
					"y": 282
				}]
			},
			{
				"name": "Wetland Aspect Radio Scanner",
				"access_rules": [
				"$Zone1Access,Wetland Aspect",
				"{Wetland Aspect}"
				],
				"sections": [{
				"name": "1",
					"clear_as_group": false,
					"item_count": 1
				}
				],
				"map_locations": [{
					"map": "map1",
					"x": 610,
					"y": 310
				}]
			},
			{
				"name": "Wetland Aspect Scavenger",
				"access_rules": [
					"{Wetland Aspect}",
					"$Zone1Access,$Zone2Access,[$Zone3Access],[$Zone4Access],[$Zone5Access],Wetland Aspect"
				],
				"sections": [{
				"name": "1",
					"clear_as_group": false,
					"item_count": 1
				}
				],
				"map_locations": [{
					"map": "map1",
					"x": 610,
					"y": 338
				}]
			},
			
			{
				"name": "Commencement",
				"access_rules": [
					"{Moon}",
					"$Zone1Access,$Zone2Access,$Zone3Access,$Zone4Access, $Zone5Access, Moon"
				],
				"sections": [{
					"name": "Commencement",
					"clear_as_group": true,
					"item_count": 1
				}],
				"map_locations": [{
					"map": "map1",
					"x": 1225,
					"y": 400
				}]
			},
			{
				"name": "Hidden Realm: Bazaar Between Time",
				"access_rules": [
					"Bazaar Between Time"
				],
				"sections": [{
					"name": "Hidden Realm: Bazaar Between Time",
					"clear_as_group": false,
					"item_count": 1
				}],
				"map_locations": [{
					"map": "map1",
					"x": 988,
					"y": 837
				}]
			},
			{
				"name": "Hidden Realm: A Moment Fractured",
				"access_rules": [
					"A Moment Fractured"
				],
				"sections": [{
					"name": "Hidden Realm: A Moment Fractured,$Zone1Access,$Zone2Access,$Zone3Access,$Zone4Access,$Zone5Access",
					"clear_as_group": false,
					"item_count": 1
				}],
				"map_locations": [{
					"map": "map1",
					"x": 988,
					"y": 660
				}]
			},
			{
				"name": "Hidden Realm: A Moment Whole",
				"access_rules": [
					"A Moment Whole,A Moment Fractured,[LunarTrinket],$Zone1Access,$Zone2Access,$Zone3Access,$Zone4Access,$Zone5Access",
					"{A Moment whole}"
				],
				"sections": [{
					"name": "Hidden Realm: A Moment Whole",
					"clear_as_group": false,
					"item_count": 1
				}],
				"map_locations": [{
					"map": "map1",
					"x": 1180,
					"y": 660
				}]
			},
			{
				"name": "Hidden Realm: Gilded Coast",
				"access_rules": [
					"Gilded Coast"
				],
				"sections": [{
					"name": "Hidden Realm: Gilded Coast",
					"clear_as_group": false,
					"item_count": 1
				}],
				"map_locations": [{
					"map": "map1",
					"x": 988,
					"y": 750
				}]
			},
			{
				"name": "Hidden Realm: Bulwark's Ambry",
				"access_rules": [
					"{Bulwarks Ambry}",
					"$Zone1Access,$Zone2Access,$Zone3Access,$Zone4Access,$Zone5Access,Bulwarks Ambry"
				],
				"sections": [{
					"name": "Hidden Realm: Bulwarks Ambry",
					"clear_as_group": false,
					"item_count": 1
				}],
				"map_locations": [{
					"map": "map1",
					"x": 1180,
					"y": 750
				}]
			},
			{
				"name": "Void Fields",
				"access_rules": [
					"{VoidFields}",
					"Bazaar Between Time, VoidFields"
				],
				"sections": [{
					"name": "Void Field",
					"clear_as_group": false,
					"item_count": 1
				}],
				"map_locations": [{
					"map": "map1",
					"x": 1180,
					"y": 837
				}]
			},
			{
				"name": "Void Locus",
				"access_rules": [
					"VoidLocus"
				],
				"sections": [{
					"name": "Void Locus,[VoidFields],[Bazaar Between Time]",
					"clear_as_group": false,
					"item_count": 1
				}],
				"map_locations": [{
					"map": "map1",
					"x": 988,
					"y": 895
				}]
			},
			{
				"name": "The Planetarium",
				"access_rules": [
					"Planetarium, VoidLocus,[VoidFields],[Bazaar Between Time],[$Zone1Access],[$Zone2Access],[$Zone3Access],[$Zone4Access],[$Zone5Access]",
					"{Planetarium,$isNotOOLPlanetarium}"
				],
				"sections": [{
					"name": "The Planetarium",
					"clear_as_group": false,
					"item_count": 1
				}],
				"map_locations": [{
					"map": "map1",
					"x": 1180,
					"y": 895
				}]
			},			
			{
				"name": "Verdant Falls Chest",
				"access_rules": [
					"Verdant Falls"
				],
				"sections": [{
				"name": "1",
					"clear_as_group": false,
					"item_count": 20
				}
				],
				"map_locations": [{
					"map": "map1",
					"x": 170,
					"y": 400
				}]
			},
			{
				"name": "Verdant Falls Shrine",
				"access_rules": [
					"Verdant Falls"
				],
				"sections": [{
				"name": "1",
					"clear_as_group": false,
					"item_count": 20
				}
				],
				"map_locations": [{
					"map": "map1",
					"x": 170,
					"y": 428
				}]
			},{
				"name": "Verdant Falls Newt Altar",
				"access_rules": [
					"Verdant Falls"
				],
				"sections": [{
				"name": "1",
					"clear_as_group": false,
					"item_count": 2
				}
				],
				"map_locations": [{
					"map": "map1",
					"x": 170,
					"y": 456
				}]
			},
			{
				"name": "Verdant Falls Radio Scanner",
				"access_rules": [
					"Verdant Falls"
				],
				"sections": [{
				"name": "1",
					"clear_as_group": false,
					"item_count": 1
				}
				],
				"map_locations": [{
					"map": "map1",
					"x": 170,
					"y": 484
				}]
			},
			{
				"name": "Verdant Falls Scavenger",
				"access_rules": [
					"[$Zone1Access],[$Zone2Access],[$Zone3Access],[$Zone4Access],[$Zone5Access],Verdant Falls"
				],
				"sections": [{
				"name": "1",
					"clear_as_group": false,
					"item_count": 1
				}
				],
				"map_locations": [{
					"map": "map1",
					"x": 170,
					"y": 512
				}]
			},
						{
				"name": "Viscous Falls Chest",
				"access_rules": [
					"Viscous Falls"
				],
				"sections": [{
				"name": "1",
					"clear_as_group": false,
					"item_count": 20
				}
				],
				"map_locations": [{
					"map": "map1",
					"x": 352,
					"y": 400
				}]
			},
			{
				"name": "Viscous Falls Shrine",
				"access_rules": [
					"Viscous Falls"
				],
				"sections": [{
				"name": "1",
					"clear_as_group": false,
					"item_count": 20
				}
				],
				"map_locations": [{
					"map": "map1",
					"x": 352,
					"y": 428
				}]
			},{
				"name": "Viscous Falls Newt Altar",
				"access_rules": [
					"Viscous Falls"
				],
				"sections": [{
				"name": "1",
					"clear_as_group": false,
					"item_count": 2
				}
				],
				"map_locations": [{
					"map": "map1",
					"x": 352,
					"y": 456
				}]
			},
			{
				"name": "Viscous Falls Radio Scanner",
				"access_rules": [
					"Viscous Falls"
				],
				"sections": [{
				"name": "1",
					"clear_as_group": false,
					"item_count": 1
				}
				],
				"map_locations": [{
					"map": "map1",
					"x": 352,
					"y": 484
				}]
			},
			{
				"name": "Viscous Falls Scavenger",
				"access_rules": [
					"[$Zone1Access],[$Zone2Access],[$Zone3Access],[$Zone4Access],[$Zone5Access],Viscous Falls"
				],
				"sections": [{
				"name": "1",
					"clear_as_group": false,
					"item_count": 1
				}
				],
				"map_locations": [{
					"map": "map1",
					"x": 352,
					"y": 512
				}]
			},
			{
				"name": "Shattered Abodes Chest",
				"access_rules": [
					"Shattered Abodes"
				],
				"sections": [{
				"name": "1",
					"clear_as_group": false,
					"item_count": 20
				}
				],
				"map_locations": [{
					"map": "map1",
					"x": 170,
					"y": 574
				}]
			},
			{
				"name": "Shattered Abodes Shrine",
				"access_rules": [
					"Shattered Abodes"
				],
				"sections": [{
				"name": "1",
					"clear_as_group": false,
					"item_count": 20
				}
				],
				"map_locations": [{
					"map": "map1",
					"x": 170,
					"y": 602
				}]
			},{
				"name": "Shattered Abodes Newt Altar",
				"access_rules": [
					"Shattered Abodes"
				],
				"sections": [{
				"name": "1",
					"clear_as_group": false,
					"item_count": 2
				}
				],
				"map_locations": [{
					"map": "map1",
					"x": 170,
					"y": 630
				}]
			},
			{
				"name": "Shattered Abodes Radio Scanner",
				"access_rules": [
					"Shattered Abodes"
				],
				"sections": [{
				"name": "1",
					"clear_as_group": false,
					"item_count": 1
				}
				],
				"map_locations": [{
					"map": "map1",
					"x": 170,
					"y": 658
				}]
			},
			{
				"name": "Shattered Abodes Scavenger",
				"access_rules": [
					"[$Zone1Access],[$Zone2Access],[$Zone3Access],[$Zone4Access],[$Zone5Access],Shattered Abodes"
				],
				"sections": [{
				"name": "1",
					"clear_as_group": false,
					"item_count": 1
				}
				],
				"map_locations": [{
					"map": "map1",
					"x": 170,
					"y": 686
				}]
			},
			{
				"name": "Disturbed Impact Chest",
				"access_rules": [
					"Disturbed Impact"
				],
				"sections": [{
				"name": "1",
					"clear_as_group": false,
					"item_count": 20
				}
				],
				"map_locations": [{
					"map": "map1",
					"x": 352,
					"y": 574
				}]
			},
			{
				"name": "Disturbed Impact Shrine",
				"access_rules": [
					"Disturbed Impact"
				],
				"sections": [{
				"name": "1",
					"clear_as_group": false,
					"item_count": 20
				}
				],
				"map_locations": [{
					"map": "map1",
					"x": 352,
					"y": 602
				}]
			},{
				"name": "Disturbed Impact Newt Altar",
				"access_rules": [
					"Disturbed Impact"
				],
				"sections": [{
				"name": "1",
					"clear_as_group": false,
					"item_count": 2
				}
				],
				"map_locations": [{
					"map": "map1",
					"x": 352,
					"y": 630
				}]
			},
			{
				"name": "Disturbed Impact Radio Scanner",
				"access_rules": [
					"Disturbed Impact"
				],
				"sections": [{
				"name": "1",
					"clear_as_group": false,
					"item_count": 1
				}
				],
				"map_locations": [{
					"map": "map1",
					"x": 352,
					"y": 658
				}]
			},
			{
				"name": "Disturbed Impact Scavenger",
				"access_rules": [
					"[$Zone1Access],[$Zone2Access],[$Zone3Access],[$Zone4Access],[$Zone5Access],Disturbed Impact"
				],
				"sections": [{
				"name": "1",
					"clear_as_group": false,
					"item_count": 1
				}
				],
				"map_locations": [{
					"map": "map1",
					"x": 352,
					"y": 686
				}]
			},
			{
				"name": "Reformed Altar Chest",
				"access_rules": [
					"{Reformed Altar}",
					"$Zone1Access,Reformed Altar"
				],
				"sections": [{
				"name": "1",
					"clear_as_group": false,
					"item_count": 20
				}
				],
				"map_locations": [{
					"map": "map1",
					"x": 610,
					"y": 574
				}]
			},
			{
				"name": "Reformed Altar Shrine",
				"access_rules": [
					"{Reformed Altar}",
					"$Zone1Access,Reformed Altar"
				],
				"sections": [{
				"name": "1",
					"clear_as_group": false,
					"item_count": 20
				}
				],
				"map_locations": [{
					"map": "map1",
					"x": 610,
					"y": 602
				}]
			},{
				"name": "Reformed Altar Newt Altar",
				"access_rules": [
					"{Reformed Altar}",
					"$Zone1Access,Reformed Altar"
				],
				"sections": [{
				"name": "1",
					"clear_as_group": false,
					"item_count": 2
				}
				],
				"map_locations": [{
					"map": "map1",
					"x": 610,
					"y": 630
				}]
			},
			{
				"name": "Reformed Altar Radio Scanner",
				"access_rules": [
					"{Reformed Altar}",
					"$Zone1Access, Reformed Altar"
				],
				"sections": [{
				"name": "1",
					"clear_as_group": false,
					"item_count": 1
				}
				],
				"map_locations": [{
					"map": "map1",
					"x": 610,
					"y": 658
				}]
			},
			{
				"name": "Reformed Altar Scavenger",
				"access_rules": [
					"Reformed Altar,$Zone1Access,[$Zone2Access],[$Zone3Access],[$Zone4Access],[$Zone5Access]"
				],
				"sections": [{
				"name": "1",
					"clear_as_group": false,
					"item_count": 1
				}
				],
				"map_locations": [{
					"map": "map1",
					"x": 610,
					"y": 686
				}]
			},
						{
				"name": "Golden Dieback Chest",
				"access_rules": [
					"{Golden Dieback}",
					"$Zone1Access,$Zone2Access,Golden Dieback,[Reformed Altar]"
				],
				"sections": [{
				"name": "1",
					"clear_as_group": false,
					"item_count": 20
				}
				],
				"map_locations": [{
					"map": "map1",
					"x": 825,
					"y": 752
				}]
			},
			{
				"name": "Golden Dieback Shrine",
				"access_rules": [
					"{Golden Dieback}",
					"$Zone1Access,$Zone2Access,Golden Dieback,[Reformed Altar]"
				],
				"sections": [{
				"name": "1",
					"clear_as_group": false,
					"item_count": 20
				}
				],
				"map_locations": [{
					"map": "map1",
					"x": 825,
					"y": 780
				}]
			},{
				"name": "Golden Dieback Newt Altar",
				"access_rules": [
					"{Golden Dieback}",
					"$Zone1Access,$Zone2Access,Golden Dieback,[Reformed Altar]"
				],
				"sections": [{
				"name": "1",
					"clear_as_group": false,
					"item_count": 2
				}
				],
				"map_locations": [{
					"map": "map1",
					"x": 825,
					"y": 808
				}]
			},
			{
				"name": "Golden Dieback Radio Scanner",
				"access_rules": [
					"{Golden Dieback}",
					"$Zone1Access,$Zone2Access,Golden Dieback,[Reformed Altar]"
				],
				"sections": [{
				"name": "1",
					"clear_as_group": false,
					"item_count": 1
				}
				],
				"map_locations": [{
					"map": "map1",
					"x": 825,
					"y": 836
				}]
			},
			{
				"name": "Golden Dieback Scavenger",
				"access_rules": [
					"$Zone1Access,$Zone2Access,[$Zone3Access],[$Zone4Access],[$Zone5Access],Golden Dieback,[Reformed Altar]"
				],
				"sections": [{
				"name": "1",
					"clear_as_group": false,
					"item_count": 1
				}
				],
				"map_locations": [{
					"map": "map1",
					"x": 825,
					"y": 864
				}]
			},
			{
				"name": "Treeborn Colony Chest",
				"access_rules": [
					"{Treeborn Colony}",
					"$Zone1Access,$Zone2Access,Treeborn Colony,[Reformed Altar]"
				],
				"sections": [{
				"name": "1",
					"clear_as_group": false,
					"item_count": 20
				}
				],
				"map_locations": [{
					"map": "map1",
					"x": 825,
					"y": 574
				}]
			},
			{
				"name": "Treeborn Colony Shrine",
				"access_rules": [
					"{Treeborn Colony}",
					"$Zone1Access,$Zone2Access,Treeborn Colony,[Reformed Altar]"
				],
				"sections": [{
				"name": "1",
					"clear_as_group": false,
					"item_count": 20
				}
				],
				"map_locations": [{
					"map": "map1",
					"x": 825,
					"y": 602
				}]
			},{
				"name": "Treeborn Colony Newt Altar",
				"access_rules": [
					"{Treeborn Colony}",
					"$Zone1Access,$Zone2Access,Treeborn Colony,[Reformed Altar]"
				],
				"sections": [{
				"name": "1",
					"clear_as_group": false,
					"item_count": 2
				}
				],
				"map_locations": [{
					"map": "map1",
					"x": 825,
					"y": 630
				}]
			},
			{
				"name": "Treeborn Colony Radio Scanner",
				"access_rules": [
					"{Treeborn Colony}",
					"$Zone1Access,$Zone2Access,Treeborn Colony,[Reformed Altar]"
				],
				"sections": [{
				"name": "1",
					"clear_as_group": false,
					"item_count": 1
				}
				],
				"map_locations": [{
					"map": "map1",
					"x": 825,
					"y": 658
				}]
			},
			{
				"name": "Treeborn Colony Scavenger",
				"access_rules": [
					"$Zone1Access,$Zone2Access,[$Zone3Access],[$Zone4Access],[$Zone5Access],Treeborn Colony,[Reformed Altar]"
				],
				"sections": [{
				"name": "1",
					"clear_as_group": false,
					"item_count": 1
				}
				],
				"map_locations": [{
					"map": "map1",
					"x": 825,
					"y": 686
				}]
			},
			{
				"name": "Prime Meridian",
				"access_rules": [
					"$Zone1Access,$Zone2Access,$Zone3Access,[$Zone4Access],[$Zone5Access],Prime Meridian,[Reformed Altar],[Golden Dieback]",
					"$Zone1Access,$Zone2Access,$Zone3Access,[$Zone4Access],[$Zone5Access],Prime Meridian,[Reformed Altar],[Treeborn Colony]",
					"{Prime Meridian,$isNotOOLPrimeMeridian}"
				],
				"sections": [{
					"name": "Prime Meridian",
					"clear_as_group": true,
					"item_count": 1
				}],
				"map_locations": [{
					"map": "map1",
					"x": 988,
					"y": 574
				}]
			},
			{
				"name": "Helminth Hatchery Chest",
				"access_rules": [
					"{Helminth Hatchery}",
					"$Zone1Access,$Zone2Access,$Zone3Access,$Zone4Access,Helminth Hatchery"
				],
				"sections": [{
				"name": "1",
					"clear_as_group": false,
					"item_count": 20
				}
				],
				"map_locations": [{
					"map": "map1",
					"x": 1290,
					"y": 226
				}]
			},
			{
				"name": "Helminth Hatchery Shrine",
								"access_rules": [
					"{Helminth Hatchery}",
					"$Zone1Access,$Zone2Access,$Zone3Access,$Zone4Access,Helminth Hatchery"
				],
				"sections": [{
				"name": "1",
					"clear_as_group": false,
					"item_count": 20
				}
				],
				"map_locations": [{
					"map": "map1",
					"x": 1290,
					"y": 254
				}]
			},{
				"name": "Helminth Hatchery Newt Altar",
								"access_rules": [
					"{Helminth Hatchery}",
					"$Zone1Access,$Zone2Access,$Zone3Access,$Zone4Access,Helminth Hatchery"
				],
				"sections": [{
				"name": "1",
					"clear_as_group": false,
					"item_count": 2
				}
				],
				"map_locations": [{
					"map": "map1",
					"x": 1290,
					"y": 282
				}]
			},
			{
				"name": "Helminth Hatchery Radio Scanner",
								"access_rules": [
					"{Helminth Hatchery}",
					"$Zone1Access,$Zone2Access,$Zone3Access,$Zone4Access,Helminth Hatchery"
				],
				"sections": [{
				"name": "1",
					"clear_as_group": false,
					"item_count": 1
				}
				],
				"map_locations": [{
					"map": "map1",
					"x": 1290,
					"y": 310
				}]
			},
			{
				"name": "Helminth Hatchery Scavenger",
				"access_rules": [
					"{Helminth Hatchery}",
					"$Zone1Access,$Zone2Access,$Zone3Access,$Zone4Access,Helminth Hatchery"
				],
				"sections": [{
				"name": "1",
					"clear_as_group": false,
					"item_count": 1
				}
				],
				"map_locations": [{
					"map": "map1",
					"x": 1290,
					"y": 338
				}]
			}
		]
	},
	{
		"name": "Classic",
		"visibility_rules": ["classicCheck"],
		"children": [{
			"name": "Item Pickup",
			"sections": [{
				"name": "ItemPickup",
				"clear_as_group": false,
				"item_count": 250
			}],
			"map_locations": [{
				"map": "map1",
				"x": 100,
				"y": 100
			}]
		}]
	}
]